main.py
sysadmin3-0.1.0.dist-info/METADATA
sysadmin3-0.1.0.dist-info/WHEEL
sysadmin3-0.1.0.dist-info/top_level.txt
sysadmin3-0.1.0.dist-info/RECORD
