Metadata-Version: 2.4
Name: sysadmin3
Version: 0.1.0
Summary: Add your description here
Requires-Python: >=3.13
Requires-Dist: colorlog>=6.10.1
Requires-Dist: concurrent-log-handler>=0.9.28
Requires-Dist: packaging>=25.0
Requires-Dist: pyqt6>=6.10.2
Requires-Dist: requests>=2.32.5
Requires-Dist: toml>=0.10.2
